helloworld.py
pytestinghelloworld-0.0.15.dist-info/METADATA
pytestinghelloworld-0.0.15.dist-info/WHEEL
pytestinghelloworld-0.0.15.dist-info/top_level.txt
pytestinghelloworld-0.0.15.dist-info/RECORD
